tomah/__init__.py
tomah/auth.py
tomah/client.py
tomah-0.0.0.dist-info/METADATA
tomah-0.0.0.dist-info/WHEEL
tomah-0.0.0.dist-info/licenses/LICENSE
tomah-0.0.0.dist-info/RECORD
